doxapy/__init__.py
doxapy/doxapy.pyd
doxapy-0.9.4.dist-info/METADATA
doxapy-0.9.4.dist-info/WHEEL
doxapy-0.9.4.dist-info/RECORD
