Metadata-Version: 2.1
Name: doxapy
Version: 0.9.4
Summary: An image binarization library focussing on local adaptive thresholding
Author-Email: "Brandon M. Petty" <brandonpetty1981@gmail.com>
License: CC0-1.0
Project-URL: Homepage, https://github.com/brandonmpetty/doxa
Requires-Python: >=3.12
Requires-Dist: numpy>=1.20.0
